template_configurator/__init__.py
template_configurator/configure.py
template_configurator/templates/.gitignore
template_configurator/templates/Makefile
template_configurator/templates/Pipfile
template_configurator/templates/README.md
template_configurator/templates/mkdocs.yml
template_configurator/templates/requirements.txt
template_configurator/templates/setup.cfg
template_configurator/templates/setup.py
template_configurator/templates/tox.ini
template_configurator/templates/.github/workflows/main.yaml
template_configurator/templates/.github/workflows/pypi-publish.yaml
template_configurator/templates/make-venv/Pipfile
template_configurator/templates/make-venv/README.md
template_configurator/templates/model/docs/credits.md
template_configurator/templates/model/docs/home.md
template_configurator/templates/model/schema/README.md
template_configurator/templates/tests/__init__.py
template_configurator/templates/tests/test_input_against_model.py
template_configurator/templates/tests/input/CONFIG.yaml
template_configurator/templates/tests/input/README.md
template_configurator-0.3.2.dist-info/AUTHORS
template_configurator-0.3.2.dist-info/METADATA
template_configurator-0.3.2.dist-info/WHEEL
template_configurator-0.3.2.dist-info/entry_points.txt
template_configurator-0.3.2.dist-info/pbr.json
template_configurator-0.3.2.dist-info/top_level.txt
template_configurator-0.3.2.dist-info/RECORD
